seagnal/evals/annotate_data.py
seagnal/evals/ft_reward_model.py
seagnal/evals/reward_model.py
seagnal/evals/size_ablation_reward.py
seagnal/evals/size_ablation_value.py
seagnal/evals/utils.py
seagnal/evals/value_model.py
seagnal/rlvr/train.py
seagnal/sft/deploy.py
seagnal/sft/merge.py
seagnal/sft/prompts.py
seagnal/sft/train.py
seagnal/sft/utils.py
seagnal-0.1.2.dist-info/METADATA
seagnal-0.1.2.dist-info/WHEEL
seagnal-0.1.2.dist-info/top_level.txt
seagnal-0.1.2.dist-info/RECORD
